[{"__type__":"cc.Prefab","_name":"action_limit_yuanzhen_panel","data":{"__id__":1}},{"__type__":"cc.Node","_name":"Layer","_children":[{"__id__":2}],"_prefab":{"__type__":"cc.PrefabInfo","root":{"__id__":1},"asset":{"__uuid__":"07zvEggmRLJJaEu30ryYqf"},"fileId":"0a7HmyKStDyqIuf1AkVxyX"},"_contentSize":{"__type__":"cc.Size","width":720,"height":908},"_trs":{"__type__":"TypedArray","ctor":"Float64Array","array":[0,0,0,0,0,0,1,1,1,1]}},{"__type__":"cc.Node","_name":"main_container","_parent":{"__id__":1},"_children":[{"__id__":3},{"__id__":11},{"__id__":12}],"_components":[{"__type__":"cc.Widget","node":{"__id__":2},"_alignFlags":18}],"_prefab":{"__type__":"cc.PrefabInfo","root":{"__id__":1},"asset":{"__uuid__":"07zvEggmRLJJaEu30ryYqf"},"fileId":"9dmDQt5iJAi6Ysj5EoX6GK"},"_contentSize":{"__type__":"cc.Size","width":720,"height":820},"_anchorPoint":{"__type__":"cc.Vec2"},"_trs":{"__type__":"TypedArray","ctor":"Float64Array","array":[-360,-410,0,0,0,0,1,1,1,1]}},{"__type__":"cc.Node","_name":"title_con","_parent":{"__id__":2},"_children":[{"__id__":4},{"__id__":5},{"__id__":6},{"__id__":7},{"__id__":10}],"_components":[{"__type__":"cc.StudioWidget","node":{"__id__":3},"_alignFlags":16,"_left":0.011099999999999999,"_bottom":0.8231999999999999,"_isAbsLeft":false,"_isAbsBottom":false}],"_prefab":{"__type__":"cc.PrefabInfo","root":{"__id__":1},"asset":{"__uuid__":"07zvEggmRLJJaEu30ryYqf"},"fileId":"32VSnUDdVOQ6Xs7qGrzoBL"},"_contentSize":{"__type__":"cc.Size","width":704,"height":145},"_anchorPoint":{"__type__":"cc.Vec2","x":0.5,"y":1},"_trs":{"__type__":"TypedArray","ctor":"Float64Array","array":[360,820.0239999999999,0,0,0,0,1,1,1,1]}},{"__type__":"cc.Node","_name":"title_img","_parent":{"__id__":3},"_components":[{"__type__":"cc.StudioWidget","node":{"__id__":4},"_alignFlags":18,"_left":0.46735,"_bottom":0.34140000000000004,"_isAbsLeft":false,"_isAbsBottom":false},{"__type__":"cc.Sprite","node":{"__id__":4},"_sizeMode":0,"_isTrimmedMode":false}],"_prefab":{"__type__":"cc.PrefabInfo","root":{"__id__":1},"asset":{"__uuid__":"07zvEggmRLJJaEu30ryYqf"},"fileId":"10jemaO35LsoaQX82+sybh"},"_contentSize":{"__type__":"cc.Size","width":712,"height":157},"_trs":{"__type__":"TypedArray","ctor":"Float64Array","array":[0,-72.5,0,0,0,0,1,1,1,1]}},{"__type__":"cc.Node","_name":"time_title","_parent":{"__id__":3},"_components":[{"__type__":"cc.Label","node":{"__id__":5},"_string":"剩余时间：","_N$string":"剩余时间：","_fontSize":20,"_lineHeight":25,"_N$horizontalAlign":1,"_N$verticalAlign":1},{"__type__":"cc.LabelOutline","node":{"__id__":5},"_color":{"__type__":"cc.Color"}}],"_prefab":{"__type__":"cc.PrefabInfo","root":{"__id__":1},"asset":{"__uuid__":"07zvEggmRLJJaEu30ryYqf"},"fileId":"c4ggJNPZJN3q9J+ftmMgsc"},"_contentSize":{"__type__":"cc.Size","width":102,"height":25},"_anchorPoint":{"__type__":"cc.Vec2","y":0.5},"_trs":{"__type__":"TypedArray","ctor":"Float64Array","array":[-339,-129.9996,0,0,0,0,1,1,1,1]}},{"__type__":"cc.Node","_name":"time_val","_parent":{"__id__":3},"_components":[{"__type__":"cc.Label","node":{"__id__":6},"_string":"00:00:00","_N$string":"00:00:00","_fontSize":20,"_lineHeight":25,"_N$horizontalAlign":1,"_N$verticalAlign":1},{"__type__":"cc.LabelOutline","node":{"__id__":6},"_color":{"__type__":"cc.Color"}}],"_prefab":{"__type__":"cc.PrefabInfo","root":{"__id__":1},"asset":{"__uuid__":"07zvEggmRLJJaEu30ryYqf"},"fileId":"a1JGHjQOhObIfMSyk2ytFg"},"_color":{"__type__":"cc.Color","r":108,"g":210,"b":40},"_contentSize":{"__type__":"cc.Size","width":79.85,"height":25},"_anchorPoint":{"__type__":"cc.Vec2","y":0.5},"_trs":{"__type__":"TypedArray","ctor":"Float64Array","array":[-246,-130,0,0,0,0,1,1,1,1]}},{"__type__":"cc.Node","_name":"common_btn","_parent":{"__id__":3},"_children":[{"__id__":8},{"__id__":9}],"_components":[{"__type__":"cc.BlockInputEvents","node":{"__id__":7}},{"__type__":"cc.Button","node":{"__id__":7},"zoomScale":0.9,"_N$transition":3,"transition":3,"_N$normalColor":{"__type__":"cc.Color","r":214,"g":214,"b":214},"_N$target":{"__id__":7}}],"_prefab":{"__type__":"cc.PrefabInfo","root":{"__id__":1},"asset":{"__uuid__":"07zvEggmRLJJaEu30ryYqf"},"fileId":"f79xNnuKdNKL+vhAcjutmN"},"_contentSize":{"__type__":"cc.Size","width":60,"height":60},"_trs":{"__type__":"TypedArray","ctor":"Float64Array","array":[287.5933,-75,0,0,0,0,1,1,1,1]}},{"__type__":"cc.Node","_name":"icon","_parent":{"__id__":7},"_components":[{"__type__":"cc.StudioWidget","node":{"__id__":8},"_alignFlags":18,"_left":0.11664999999999998,"_bottom":0.11664999999999998,"_isAbsLeft":false,"_isAbsBottom":false},{"__type__":"cc.Sprite","node":{"__id__":8},"_sizeMode":2,"_isTrimmedMode":false}],"_prefab":{"__type__":"cc.PrefabInfo","root":{"__id__":1},"asset":{"__uuid__":"07zvEggmRLJJaEu30ryYqf"},"fileId":"fbcLvUepJDcr/+P0NIf1lh"},"_contentSize":{"__type__":"cc.Size","width":46,"height":46},"_trs":{"__type__":"TypedArray","ctor":"Float64Array","array":[0,0,0,0,0,0,1,1,1,1]}},{"__type__":"cc.Node","_name":"label","_parent":{"__id__":7},"_components":[{"__type__":"cc.StudioWidget","node":{"__id__":9},"_alignFlags":16,"_left":-0.09166666666666667,"_isAbsLeft":false},{"__type__":"cc.Label","node":{"__id__":9},"_string":"按钮名字","_N$string":"按钮名字","_fontSize":18,"_lineHeight":22,"_N$horizontalAlign":1,"_N$verticalAlign":1},{"__type__":"cc.LabelOutline","node":{"__id__":9},"_color":{"__type__":"cc.Color"},"_width":2}],"_prefab":{"__type__":"cc.PrefabInfo","root":{"__id__":1},"asset":{"__uuid__":"07zvEggmRLJJaEu30ryYqf"},"fileId":"6bwMk6GUtERagPykNu7Onc"},"_color":{"__type__":"cc.Color","r":255,"g":231,"b":190},"_contentSize":{"__type__":"cc.Size","width":76,"height":22},"_trs":{"__type__":"TypedArray","ctor":"Float64Array","array":[0,-38,0,0,0,0,1,1,1,1]}},{"__type__":"cc.Node","_name":"title_desc","_parent":{"__id__":3},"_components":[{"__type__":"cc.Label","node":{"__id__":10},"_useOriginalSize":false,"_string":"Label","_N$string":"Label","_fontSize":18,"_lineHeight":20,"_N$horizontalAlign":1,"_N$verticalAlign":1}],"_prefab":{"__type__":"cc.PrefabInfo","root":{"__id__":1},"asset":{"__uuid__":"07zvEggmRLJJaEu30ryYqf"},"fileId":"43f6sx5xlCw6N0l6hp8ZIU"},"_color":{"__type__":"cc.Color","r":247,"g":230,"b":176},"_contentSize":{"__type__":"cc.Size","width":44.04,"height":20},"_anchorPoint":{"__type__":"cc.Vec2","y":0.5},"_trs":{"__type__":"TypedArray","ctor":"Float64Array","array":[-302,-69,0,0,0,0,1,1,1,1]}},{"__type__":"cc.Node","_name":"goods_con","_parent":{"__id__":2},"_components":[{"__type__":"cc.StudioWidget","node":{"__id__":11},"_alignFlags":18,"_left":0.022199999999999998,"_verticalCenter":-70,"_isAbsLeft":false}],"_prefab":{"__type__":"cc.PrefabInfo","root":{"__id__":1},"asset":{"__uuid__":"07zvEggmRLJJaEu30ryYqf"},"fileId":"76tLSMJBhGQrOsFwTMpOcw"},"_contentSize":{"__type__":"cc.Size","width":688,"height":650},"_anchorPoint":{"__type__":"cc.Vec2"},"_trs":{"__type__":"TypedArray","ctor":"Float64Array","array":[16,15,0,0,0,0,1,1,1,1]}},{"__type__":"cc.Node","_name":"Sprite_4","_parent":{"__id__":2},"_components":[{"__type__":"cc.Sprite","node":{"__id__":12},"_sizeMode":2,"_isTrimmedMode":false}],"_prefab":{"__type__":"cc.PrefabInfo","root":{"__id__":1},"asset":{"__uuid__":"07zvEggmRLJJaEu30ryYqf"},"fileId":"7f6h2XRwJNiojYqLRTjhPX"},"_contentSize":{"__type__":"cc.Size","width":33,"height":44},"_trs":{"__type__":"TypedArray","ctor":"Float64Array","array":[360,0,0,0,0,0,1,1,1,1]},"_eulerAngles":{"__type__":"cc.Vec3","z":-90}}]