[{"__type__":"cc.Prefab","_name":"guildwar_defend_look_window","data":{"__id__":1}},{"__type__":"cc.Node","_name":"root_wnd","_children":[{"__id__":2},{"__id__":3}],"_prefab":{"__type__":"cc.PrefabInfo","root":{"__id__":1},"asset":{"__uuid__":"20mOt7/ZFBmZQuspqJEhdT"},"fileId":"5dEn84/JFJy7LKTtWqzfMT"},"_contentSize":{"__type__":"cc.Size","width":720,"height":1280},"_anchorPoint":{"__type__":"cc.Vec2"},"_trs":{"__type__":"TypedArray","ctor":"Float64Array","array":[0,0,0,0,0,0,1,1,1,1]}},{"__type__":"cc.Node","_name":"background","_parent":{"__id__":1},"_components":[{"__type__":"cc.Sprite","node":{"__id__":2},"_spriteFrame":{"__uuid__":"a2MjXRFdtLlYQ5ouAFv/+R"},"_sizeMode":0,"_isTrimmedMode":false},{"__type__":"cc.StudioWidget","node":{"__id__":2},"_alignFlags":18},{"__type__":"cc.BlockInputEvents","node":{"__id__":2}}],"_prefab":{"__type__":"cc.PrefabInfo","root":{"__id__":1},"asset":{"__uuid__":"20mOt7/ZFBmZQuspqJEhdT"},"fileId":"06FgxfPE5D85vGDFOn55EM"},"_opacity":102,"_color":{"__type__":"cc.Color"},"_contentSize":{"__type__":"cc.Size","width":720,"height":1280},"_trs":{"__type__":"TypedArray","ctor":"Float64Array","array":[360,640,0,0,0,0,1,1,1,1]}},{"__type__":"cc.Node","_name":"container","_parent":{"__id__":1},"_children":[{"__id__":4},{"__id__":6},{"__id__":7},{"__id__":8},{"__id__":9},{"__id__":10},{"__id__":11},{"__id__":12},{"__id__":13},{"__id__":14},{"__id__":15},{"__id__":16},{"__id__":17},{"__id__":18},{"__id__":19},{"__id__":20}],"_components":[{"__type__":"cc.BlockInputEvents","node":{"__id__":3}}],"_prefab":{"__type__":"cc.PrefabInfo","root":{"__id__":1},"asset":{"__uuid__":"20mOt7/ZFBmZQuspqJEhdT"},"fileId":"e1FRGw57FL7b0oBgCGf6UA"},"_contentSize":{"__type__":"cc.Size","width":676,"height":918},"_trs":{"__type__":"TypedArray","ctor":"Float64Array","array":[360,640,0,0,0,0,1,1,1,1]}},{"__type__":"cc.Node","_name":"main_panel","_parent":{"__id__":3},"_children":[{"__id__":5}],"_components":[{"__type__":"cc.BlockInputEvents","node":{"__id__":4}}],"_prefab":{"__type__":"cc.PrefabInfo","root":{"__id__":1},"asset":{"__uuid__":"20mOt7/ZFBmZQuspqJEhdT"},"fileId":"8498uP6ztA66Tak4MMaKHt"},"_contentSize":{"__type__":"cc.Size","width":676,"height":918},"_trs":{"__type__":"TypedArray","ctor":"Float64Array","array":[0.5008000000000266,-0.410000000000025,0,0,0,0,1,1,1,1]}},{"__type__":"cc.Node","_name":"background","_parent":{"__id__":4},"_components":[{"__type__":"cc.Sprite","node":{"__id__":5},"_spriteFrame":{"__uuid__":"d4xHPooIBK66IRUuGLsSQB"},"_type":1,"_sizeMode":0,"_isTrimmedMode":false},{"__type__":"cc.StudioWidget","node":{"__id__":5},"_alignFlags":18}],"_prefab":{"__type__":"cc.PrefabInfo","root":{"__id__":1},"asset":{"__uuid__":"20mOt7/ZFBmZQuspqJEhdT"},"fileId":"61+F/iOchAlImn59PBMhH4"},"_contentSize":{"__type__":"cc.Size","width":676,"height":918},"_trs":{"__type__":"TypedArray","ctor":"Float64Array","array":[0,0,0,0,0,0,1,1,1,1]}},{"__type__":"cc.Node","_name":"image_1","_parent":{"__id__":3},"_components":[{"__type__":"cc.Sprite","node":{"__id__":6},"_spriteFrame":{"__uuid__":"17+4At1HlCXoK+lb17Xt5T"},"_type":1,"_sizeMode":0,"_isTrimmedMode":false}],"_prefab":{"__type__":"cc.PrefabInfo","root":{"__id__":1},"asset":{"__uuid__":"20mOt7/ZFBmZQuspqJEhdT"},"fileId":"f2effNHh1DEb5jfZKkWlrQ"},"_contentSize":{"__type__":"cc.Size","width":644,"height":860},"_anchorPoint":{"__type__":"cc.Vec2"},"_trs":{"__type__":"TypedArray","ctor":"Float64Array","array":[-321,-441.6848,0,0,0,0,1,1,1,1]}},{"__type__":"cc.Node","_name":"image_2","_parent":{"__id__":3},"_components":[{"__type__":"cc.Sprite","node":{"__id__":7},"_type":1,"_sizeMode":0,"_isTrimmedMode":false}],"_prefab":{"__type__":"cc.PrefabInfo","root":{"__id__":1},"asset":{"__uuid__":"20mOt7/ZFBmZQuspqJEhdT"},"fileId":"35E52PEktJy6KtRnoHjrYH"},"_contentSize":{"__type__":"cc.Size","width":261,"height":54},"_trs":{"__type__":"TypedArray","ctor":"Float64Array","array":[0,453,0,0,0,0,1,1,1,1]}},{"__type__":"cc.Node","_name":"list_bg","_parent":{"__id__":3},"_components":[{"__type__":"cc.Sprite","node":{"__id__":8},"_spriteFrame":{"__uuid__":"7fCDNrGQBO7p3kFR3Y3DcO"},"_type":1,"_sizeMode":0,"_isTrimmedMode":false}],"_prefab":{"__type__":"cc.PrefabInfo","root":{"__id__":1},"asset":{"__uuid__":"20mOt7/ZFBmZQuspqJEhdT"},"fileId":"d0QvIfeXxDIaYIVVcwx8OL"},"_contentSize":{"__type__":"cc.Size","width":622,"height":530},"_trs":{"__type__":"TypedArray","ctor":"Float64Array","array":[0.006199999999978445,-138,0,0,0,0,1,1,1,1]}},{"__type__":"cc.Node","_name":"line_1","_parent":{"__id__":3},"_components":[{"__type__":"cc.Sprite","node":{"__id__":9},"_spriteFrame":{"__uuid__":"874oInw5dPRbu2R1isMrx3"},"_sizeMode":0,"_isTrimmedMode":false}],"_prefab":{"__type__":"cc.PrefabInfo","root":{"__id__":1},"asset":{"__uuid__":"20mOt7/ZFBmZQuspqJEhdT"},"fileId":"b5K7nva/JH3oe23Pc+wYKL"},"_contentSize":{"__type__":"cc.Size","width":124,"height":10},"_anchorPoint":{"__type__":"cc.Vec2","x":1,"y":0.5},"_trs":{"__type__":"TypedArray","ctor":"Float64Array","array":[-82.9999,383,0,0,0,0,1,1,1,1]}},{"__type__":"cc.Node","_name":"line_2","_parent":{"__id__":3},"_components":[{"__type__":"cc.Sprite","node":{"__id__":10},"_spriteFrame":{"__uuid__":"874oInw5dPRbu2R1isMrx3"},"_sizeMode":0,"_isTrimmedMode":false}],"_prefab":{"__type__":"cc.PrefabInfo","root":{"__id__":1},"asset":{"__uuid__":"20mOt7/ZFBmZQuspqJEhdT"},"fileId":"0evIM1BPxMUqBwa+llLkyT"},"_contentSize":{"__type__":"cc.Size","width":124,"height":10},"_anchorPoint":{"__type__":"cc.Vec2","x":1,"y":0.5},"_trs":{"__type__":"TypedArray","ctor":"Float64Array","array":[82.99939999999998,382.9996,0,0,0,0,1,-1,1,1]}},{"__type__":"cc.Node","_name":"line_3","_parent":{"__id__":3},"_components":[{"__type__":"cc.Sprite","node":{"__id__":11},"_spriteFrame":{"__uuid__":"874oInw5dPRbu2R1isMrx3"},"_sizeMode":0,"_isTrimmedMode":false}],"_prefab":{"__type__":"cc.PrefabInfo","root":{"__id__":1},"asset":{"__uuid__":"20mOt7/ZFBmZQuspqJEhdT"},"fileId":"46zrA4ji1C26sYv0MMnamM"},"_contentSize":{"__type__":"cc.Size","width":124,"height":10},"_anchorPoint":{"__type__":"cc.Vec2","x":1,"y":0.5},"_trs":{"__type__":"TypedArray","ctor":"Float64Array","array":[-63,143,0,0,0,0,1,1,1,1]}},{"__type__":"cc.Node","_name":"line_4","_parent":{"__id__":3},"_components":[{"__type__":"cc.Sprite","node":{"__id__":12},"_spriteFrame":{"__uuid__":"874oInw5dPRbu2R1isMrx3"},"_sizeMode":0,"_isTrimmedMode":false}],"_prefab":{"__type__":"cc.PrefabInfo","root":{"__id__":1},"asset":{"__uuid__":"20mOt7/ZFBmZQuspqJEhdT"},"fileId":"56NkUmYRBO6bsHdVgZCdoy"},"_contentSize":{"__type__":"cc.Size","width":124,"height":10},"_anchorPoint":{"__type__":"cc.Vec2","x":1,"y":0.5},"_trs":{"__type__":"TypedArray","ctor":"Float64Array","array":[62.999900000000025,143,0,0,0,0,1,-1,1,1]}},{"__type__":"cc.Node","_name":"close_btn","_parent":{"__id__":3},"_components":[{"__type__":"cc.BlockInputEvents","node":{"__id__":13}},{"__type__":"cc.Button","node":{"__id__":13},"zoomScale":0.9,"_N$transition":3,"transition":3,"_N$normalColor":{"__type__":"cc.Color","r":214,"g":214,"b":214},"_N$normalSprite":{"__uuid__":"3dnZ3mDIhKHbTx6ZZWLnaH"},"_N$pressedSprite":{"__uuid__":"e97GVMl6JHh5Ml5qEDdSGa"},"pressedSprite":{"__uuid__":"e97GVMl6JHh5Ml5qEDdSGa"},"_N$disabledSprite":{"__uuid__":"29FYIk+N1GYaeWH/q1NxQO"}},{"__type__":"cc.Sprite","node":{"__id__":13},"_spriteFrame":{"__uuid__":"3dnZ3mDIhKHbTx6ZZWLnaH"},"_sizeMode":0,"_isTrimmedMode":false}],"_prefab":{"__type__":"cc.PrefabInfo","root":{"__id__":1},"asset":{"__uuid__":"20mOt7/ZFBmZQuspqJEhdT"},"fileId":"66FQLfYf1OYJXV0MUbgY7c"},"_contentSize":{"__type__":"cc.Size","width":59,"height":71},"_trs":{"__type__":"TypedArray","ctor":"Float64Array","array":[321,438,0,0,0,0,1,1,1,1]}},{"__type__":"cc.Node","_name":"win_title","_parent":{"__id__":3},"_components":[{"__type__":"cc.Label","node":{"__id__":14},"_string":"防守记录","_N$string":"防守记录","_fontSize":26,"_lineHeight":30,"_N$verticalAlign":1},{"__type__":"cc.LabelOutline","node":{"__id__":14},"_color":{"__type__":"cc.Color","r":75,"g":33,"b":10}}],"_prefab":{"__type__":"cc.PrefabInfo","root":{"__id__":1},"asset":{"__uuid__":"20mOt7/ZFBmZQuspqJEhdT"},"fileId":"66GvYAbjlJiLCPZP9SdtoM"},"_color":{"__type__":"cc.Color","r":249,"g":241,"b":221},"_contentSize":{"__type__":"cc.Size","width":106,"height":30},"_trs":{"__type__":"TypedArray","ctor":"Float64Array","array":[0,459,0,0,0,0,1,1,1,1]}},{"__type__":"cc.Node","_name":"title_label_1","_parent":{"__id__":3},"_components":[{"__type__":"cc.StudioWidget","node":{"__id__":15},"_alignFlags":8,"_left":0.3934689349112426,"_isAbsLeft":false},{"__type__":"cc.Label","node":{"__id__":15},"_string":"据点防守阵容","_N$string":"据点防守阵容","_fontSize":24,"_lineHeight":30,"_N$verticalAlign":1}],"_prefab":{"__type__":"cc.PrefabInfo","root":{"__id__":1},"asset":{"__uuid__":"20mOt7/ZFBmZQuspqJEhdT"},"fileId":"7a2sQqhS9OqIaFWpRnKCLo"},"_color":{"__type__":"cc.Color","r":104,"g":69,"b":42},"_contentSize":{"__type__":"cc.Size","width":144,"height":30},"_trs":{"__type__":"TypedArray","ctor":"Float64Array","array":[-0.015000000000043201,383,0,0,0,0,1,1,1,1]}},{"__type__":"cc.Node","_name":"title_label_2","_parent":{"__id__":3},"_components":[{"__type__":"cc.StudioWidget","node":{"__id__":16},"_alignFlags":8,"_left":0.4290189349112426,"_isAbsLeft":false},{"__type__":"cc.Label","node":{"__id__":16},"_string":"防守录像","_N$string":"防守录像","_fontSize":24,"_lineHeight":30,"_N$verticalAlign":1}],"_prefab":{"__type__":"cc.PrefabInfo","root":{"__id__":1},"asset":{"__uuid__":"20mOt7/ZFBmZQuspqJEhdT"},"fileId":"b2YlxOuUxMr4ospKo/m88A"},"_color":{"__type__":"cc.Color","r":104,"g":69,"b":42},"_contentSize":{"__type__":"cc.Size","width":96,"height":30},"_trs":{"__type__":"TypedArray","ctor":"Float64Array","array":[0.016799999999989268,143,0,0,0,0,1,1,1,1]}},{"__type__":"cc.Node","_name":"time_label","_parent":{"__id__":3},"_components":[{"__type__":"cc.Label","node":{"__id__":17},"_string":"每周四20:00:00-22:00：00进行","_N$string":"每周四20:00:00-22:00：00进行","_fontSize":24,"_lineHeight":30,"_N$verticalAlign":1}],"_prefab":{"__type__":"cc.PrefabInfo","root":{"__id__":1},"asset":{"__uuid__":"20mOt7/ZFBmZQuspqJEhdT"},"fileId":"a4aIoHVJFEJ7xwpa+AQeDQ"},"_color":{"__type__":"cc.Color","r":104,"g":69,"b":42},"_contentSize":{"__type__":"cc.Size","width":332.17,"height":30},"_anchorPoint":{"__type__":"cc.Vec2","x":1,"y":0.5},"_trs":{"__type__":"TypedArray","ctor":"Float64Array","array":[312,-421,0,0,0,0,1,1,1,1]}},{"__type__":"cc.Node","_name":"no_vedio_image","_parent":{"__id__":3},"_components":[{"__type__":"cc.Sprite","node":{"__id__":18},"_spriteFrame":{"__uuid__":"65z/EB/ipJfpSL7dGj7wjt"},"_sizeMode":0,"_isTrimmedMode":false}],"_prefab":{"__type__":"cc.PrefabInfo","root":{"__id__":1},"asset":{"__uuid__":"20mOt7/ZFBmZQuspqJEhdT"},"fileId":"4dMM9+QqVD557KYK/Y8iBj"},"_contentSize":{"__type__":"cc.Size","width":250,"height":122},"_trs":{"__type__":"TypedArray","ctor":"Float64Array","array":[0,-99,0,0,0,0,1,1,1,1]}},{"__type__":"cc.Node","_name":"no_vedio_label","_parent":{"__id__":3},"_components":[{"__type__":"cc.Label","node":{"__id__":19},"_string":"暂无挑战记录","_N$string":"暂无挑战记录","_fontSize":26,"_lineHeight":30,"_N$verticalAlign":1}],"_prefab":{"__type__":"cc.PrefabInfo","root":{"__id__":1},"asset":{"__uuid__":"20mOt7/ZFBmZQuspqJEhdT"},"fileId":"d6EAwxwlxNSb0Cn1rUoNbh"},"_color":{"__type__":"cc.Color","r":253,"g":226,"b":189},"_contentSize":{"__type__":"cc.Size","width":156,"height":30},"_trs":{"__type__":"TypedArray","ctor":"Float64Array","array":[0,-184,0,0,0,0,1,1,1,1]}},{"__type__":"cc.Node","_name":"list_panel","_parent":{"__id__":3},"_components":[{"__type__":"cc.BlockInputEvents","node":{"__id__":20}}],"_prefab":{"__type__":"cc.PrefabInfo","root":{"__id__":1},"asset":{"__uuid__":"20mOt7/ZFBmZQuspqJEhdT"},"fileId":"97wsEI3OFOKqkI8V+Swb7Y"},"_contentSize":{"__type__":"cc.Size","width":616,"height":520},"_trs":{"__type__":"TypedArray","ctor":"Float64Array","array":[0,-139,0,0,0,0,1,1,1,1]}}]