{"__type__":"sp.SkeletonData","_name":"action1","_skeletonJson":{"skeleton":{"hash":"ALcb1IkPy8s6ziz0ArnpYJY/lWs","spine":"3.5.49","width":0,"height":0,"images":"./images/"},"bones":[{"name":"root"}],"slots":[{"name":"action11","bone":"root"}],"skins":{"default":{"action11":{"action10000":{"width":505,"height":505},"action10001":{"width":505,"height":505},"action10002":{"width":505,"height":505},"action10003":{"width":505,"height":505},"action10004":{"width":505,"height":505},"action10005":{"width":505,"height":505},"action10006":{"width":505,"height":505},"action10007":{"width":505,"height":505},"action10008":{"width":505,"height":505},"action10009":{"width":505,"height":505}}}},"events":{"attack":{},"back":{},"hit":{},"hit_num1":{},"move":{},"ready":{},"shake_point":{}},"animations":{"action1":{"slots":{"action11":{"attachment":[{"time":0,"name":"action10000"},{"time":0.1333,"name":"action10001"},{"time":0.2667,"name":"action10002"},{"time":0.3667,"name":"action10003"},{"time":0.4667,"name":"action10004"},{"time":0.5333,"name":"action10005"},{"time":0.6333,"name":"action10006"},{"time":0.7667,"name":"action10007"},{"time":0.8667,"name":"action10008"},{"time":1,"name":"action10009"},{"time":1.1333,"name":"action10000"}]}},"events":[{"time":0,"name":"ready"},{"time":0.7,"name":"attack"},{"time":0.8667,"name":"hit"}]},"action2":{"slots":{"action11":{"attachment":[{"time":0,"name":"action10000"},{"time":0.1333,"name":"action10001"},{"time":0.2667,"name":"action10002"},{"time":0.3667,"name":"action10003"},{"time":0.4667,"name":"action10004"},{"time":0.5333,"name":"action10005"},{"time":0.6333,"name":"action10006"},{"time":0.7667,"name":"action10007"},{"time":0.8667,"name":"action10008"},{"time":1,"name":"action10009"},{"time":1.1333,"name":"action10000"}]}},"events":[{"time":0,"name":"ready"},{"time":0.5333,"name":"attack"},{"time":0.7667,"name":"hit"}]}}},"_atlasText":"\r\naction1.png\r\nsize: 355,576\r\nformat: RGBA8888\r\nfilter: Linear,Linear\r\nrepeat: none\r\naction10000\r\n  rotate: false\r\n  xy: 2, 432\r\n  size: 130, 142\r\n  orig: 505, 505\r\n  offset: 191, 240\r\n  index: -1\r\naction10001\r\n  rotate: false\r\n  xy: 2, 2\r\n  size: 120, 140\r\n  orig: 505, 505\r\n  offset: 188, 238\r\n  index: -1\r\naction10002\r\n  rotate: false\r\n  xy: 2, 144\r\n  size: 125, 143\r\n  orig: 505, 505\r\n  offset: 180, 237\r\n  index: -1\r\naction10003\r\n  rotate: false\r\n  xy: 129, 135\r\n  size: 111, 152\r\n  orig: 505, 505\r\n  offset: 185, 241\r\n  index: -1\r\naction10004\r\n  rotate: false\r\n  xy: 247, 287\r\n  size: 106, 147\r\n  orig: 505, 505\r\n  offset: 186, 248\r\n  index: -1\r\naction10005\r\n  rotate: false\r\n  xy: 242, 142\r\n  size: 105, 143\r\n  orig: 505, 505\r\n  offset: 184, 253\r\n  index: -1\r\naction10006\r\n  rotate: false\r\n  xy: 133, 294\r\n  size: 112, 136\r\n  orig: 505, 505\r\n  offset: 181, 254\r\n  index: -1\r\naction10007\r\n  rotate: true\r\n  xy: 124, 3\r\n  size: 130, 134\r\n  orig: 505, 505\r\n  offset: 170, 244\r\n  index: -1\r\naction10008\r\n  rotate: true\r\n  xy: 2, 289\r\n  size: 141, 129\r\n  orig: 505, 505\r\n  offset: 168, 249\r\n  index: -1\r\naction10009\r\n  rotate: false\r\n  xy: 134, 436\r\n  size: 131, 138\r\n  orig: 505, 505\r\n  offset: 184, 244\r\n  index: -1\r\n","textures":[{"__uuid__":"5dtcPYsxNH+q4Cersp4P+H"}],"textureNames":["action1.png"]}