{"__type__":"sp.SkeletonData","_name":"action2","_skeletonJson":{"skeleton":{"hash":"CIoa/roEvZ9pxhPjF65dhgAxTwc","spine":"3.5.49","width":0,"height":0,"images":"./images/"},"bones":[{"name":"root"}],"slots":[{"name":"action22","bone":"root"}],"skins":{"default":{"action22":{"action20000":{"width":515,"height":515},"action20001":{"width":515,"height":515},"action20002":{"width":515,"height":515},"action20003":{"width":515,"height":515},"action20004":{"width":515,"height":515},"action20005":{"width":515,"height":515},"action20006":{"width":515,"height":515},"action20007":{"width":515,"height":515},"action20008":{"width":515,"height":515},"action20009":{"width":515,"height":515},"action20010":{"width":515,"height":515}}}},"events":{"attack":{},"back":{},"hit":{},"move":{},"ready":{},"shake_point":{}},"animations":{"action2":{"slots":{"action22":{"attachment":[{"time":0,"name":"action20000"},{"time":0.1,"name":"action20001"},{"time":0.2,"name":"action20002"},{"time":0.3,"name":"action20003"},{"time":0.4,"name":"action20004"},{"time":0.5,"name":"action20005"},{"time":0.6,"name":"action20006"},{"time":0.7,"name":"action20007"},{"time":0.8,"name":"action20008"},{"time":0.9,"name":"action20009"},{"time":1,"name":"action20010"},{"time":1.1,"name":"action20000"}]}},"events":[{"time":0,"name":"ready"},{"time":0.0333,"name":"move"},{"time":0.1,"name":"attack"},{"time":0.6,"name":"hit"},{"time":1.0333,"name":"back"}]}}},"_atlasText":"\r\naction2.png\r\nsize: 213,565\r\nformat: RGBA8888\r\nfilter: Linear,Linear\r\nrepeat: none\r\naction20000\r\n  rotate: false\r\n  xy: 2, 2\r\n  size: 73, 108\r\n  orig: 515, 515\r\n  offset: 210, 256\r\n  index: -1\r\naction20001\r\n  rotate: false\r\n  xy: 134, 449\r\n  size: 75, 114\r\n  orig: 515, 515\r\n  offset: 209, 254\r\n  index: -1\r\naction20002\r\n  rotate: false\r\n  xy: 2, 223\r\n  size: 110, 104\r\n  orig: 515, 515\r\n  offset: 199, 255\r\n  index: -1\r\naction20003\r\n  rotate: false\r\n  xy: 77, 6\r\n  size: 97, 104\r\n  orig: 515, 515\r\n  offset: 202, 258\r\n  index: -1\r\naction20004\r\n  rotate: true\r\n  xy: 2, 329\r\n  size: 88, 114\r\n  orig: 515, 515\r\n  offset: 229, 275\r\n  index: -1\r\naction20005\r\n  rotate: true\r\n  xy: 2, 500\r\n  size: 63, 130\r\n  orig: 515, 515\r\n  offset: 220, 282\r\n  index: -1\r\naction20006\r\n  rotate: true\r\n  xy: 2, 419\r\n  size: 79, 125\r\n  orig: 515, 515\r\n  offset: 205, 286\r\n  index: -1\r\naction20007\r\n  rotate: false\r\n  xy: 129, 335\r\n  size: 82, 112\r\n  orig: 515, 515\r\n  offset: 200, 288\r\n  index: -1\r\naction20008\r\n  rotate: false\r\n  xy: 118, 221\r\n  size: 92, 112\r\n  orig: 515, 515\r\n  offset: 192, 288\r\n  index: -1\r\naction20009\r\n  rotate: false\r\n  xy: 114, 112\r\n  size: 97, 107\r\n  orig: 515, 515\r\n  offset: 190, 285\r\n  index: -1\r\naction20010\r\n  rotate: true\r\n  xy: 2, 129\r\n  size: 92, 110\r\n  orig: 515, 515\r\n  offset: 195, 273\r\n  index: -1\r\n","textures":[{"__uuid__":"5fVWlGrC1E/onBFQucKGJy"}],"textureNames":["action2.png"]}